prácticas/p1.2/mods/mux4_1.v

module mux4_1 (output reg out, input wire e0, e1, e2, e3, input wire [1:0] s);

always@ (e0, e1, e2, e3, s)
	begin
	case(s)
		2'b00 : out = e0;
		2'b01 : out = e1;
		2'b10 : out = e2;
		2'b11 : out = e3;
		default: out = 1'bx;
	endcase
	end

endmodule

prácticas/p1.2/mods/compl1.v

module compl1 (output wire [3:0] Sal, input wire [3:0] Ent, input wire cpl);

	assign Sal = cpl ? ~Ent : Ent;

endmodule

prácticas/p1.2/mods/mux2_4.v
module mux2_4(output wire [3:0] out, input wire [3:0] a, input wire [3:0] b, input wire s);

	assign out = s ? b : a; //oper. condicional de C, sintaxis [condicion ? valor_si_cierta : valor_si_falsa] 

endmodule

prácticas/p1.2/mods/mux2_1.v
module mux2_1(output wire out, input wire a, input wire b, input wire s);

	assign out = s ? b : a; //oper. condicional de C, sintaxis [condicion ? valor_si_cierta : valor_si_falsa] 

endmodule

prácticas/p1.2/mods/cl_c.v
module cl (output reg out, input wire a, b, input wire [1:0] s);

always@ (a, b, s)
    begin
    case(s)
        2'b00 : out = a&b;
        2'b01 : out = a|b;
        2'b10 : out = a^b;
        2'b11 : out = ~a;
        default: out = 1'bx;
    endcase
    end

endmodule

prácticas/p1.2/mods/fa.v

module fa (output wire cout, sum, input wire a, b, cin);

	assign {cout, sum} = a + b + cin;

endmodule

prácticas/p1.2/mods/cal.v
// celda aritmético-lógica
module cal (output wire out, c_out, input wire a, b, l, c_in, input wire [1:0] s);

	// sum_inner: salida del full adder (fa), 
	// cl_inne: salida de la celda lógica (cl)
	wire sum_inner, cl_inner;	

	fa fa1 (c_out, sum_inner, a, b, c_in);
	cl cl1 (cl_inner, a, b, s);
	
	// mux 2 a 1, 
	// si l=1, cl_int -> out
	// si l=0, sum_int -> out
	// assign out = l ? cl_inner : sum_inner;
	mux2_1 mux1(out, sum_inner, cl_inner, l);

endmodule

prácticas/p1.2/mods/alu.v
module alu(output wire [3:0] R, output wire zero, carry, sign, input wire [3:0] A, B, input wire [1:0] ALUOp, input wire L);

wire [3:0] carry_inner;
wire [3:0] OP1, OP2, OP_inner;
wire op1_A, op2_B, cpl, cin;

// Conexiones en serie de los cal
cal cal1(R[0], carry_inner[1], OP1[0], OP2[0], L, cin,            ALUOp);
cal cal2(R[1], carry_inner[2], OP1[1], OP2[1], L, carry_inner[1], ALUOp);
cal cal3(R[2], carry_inner[3], OP1[2], OP2[2], L, carry_inner[2], ALUOp);
cal cal4(R[3], carry,          OP1[3], OP2[3], L, carry_inner[3], ALUOp);

// MUX
mux2_4 mux2_A(OP1,      4'b0000, A, op1_A);
mux2_4 mux2_B(OP_inner, A      , B, op2_B);

// Complemento a 1
compl1 cpl1(OP2, OP_inner, cpl);

// Diseño de funciones lógicas que controlan los mux y cpls (Karnaughs)
assign op1_A = L | (~ALUOp[1]);
assign op2_B = L | (~ALUOp[1]) |  ALUOp[0];
assign cin   = ALUOp[1] | ALUOp[0];
assign cpl   = (~L & ALUOp[1]) | (~L & ALUOp[0]); // Complemento a 1

//Funciones lógicas de los flags zero, acarreo y signo
//assign zero  = (R == 4'b0000)? 1'b1: 1'b0;
//mux2_1 zero_mux(zero, 1'b0, 1'b1, R[3]); // modificación 2
// Q = (A * S) + (B * S')

wire out_big_or;
or check_ones(out_big_or, R[0], R[1], R[2], R[3]);
not inv_or(zero, out_big_or);


assign sign  =  R[3];
// acarreo inherente en las conexiones en serie de los cal.



endmodule

prácticas/p1.2/mods/alu_tb.v
// Testbench para modulo alu
`timescale 1 ns / 10 ps //Directiva que fija la unidad de tiempo de simulación y la precision de la unidad
module alu_tb;
//declaracion de señales
reg [1:0] t_Op;
reg t_L;
reg [3:0] t_A, t_B;
wire [3:0] t_R;
wire t_z, t_c, t_s;
integer errores;
//instancia del modulo a testear
alu mat(t_R, t_z, t_c, t_s, t_A, t_B, t_Op, t_L);

initial
begin
  $dumpfile("alu.vcd");
  $dumpvars;
/*  $monitor("tiempo=%0d A=%b B=%b L=%b Op=%b R=%b, Z=%b, C=%b, S=%b", $time, t_A, t_B, t_L, t_Op, t_R, t_z, t_c, t_s);
*/
  errores = 0;
  t_L = 1'b0;
  repeat(2)
	begin
	t_Op = 2'b0;
	repeat(4)
		begin
		  t_A = 4'b0;
		  repeat(16) 
		  begin
			t_B = 4'b0;
			repeat(16) 
			begin
				# 2 check;
				t_B = t_B + 1;
			end
			t_A = t_A + 1;
		  end
		  t_Op = t_Op + 1;
		end
		t_L = t_L + 1;
	end
	$display("Encontradas %d operaciones erroneas", errores);
  //fin simulacion
  $finish;
end

// Tarea para hacer la comprobación automática de resultados
task check;
reg [4:0] result;
reg flag_zero, flag_carry, flag_sign;
begin
	// Si las operaciones son lógicas
	if (t_L)
	begin
		case (t_Op)
			2'b00: result[3:0] = t_A & t_B;
			2'b01: result[3:0] = t_A | t_B;
			2'b10: result[3:0] = t_A ^ t_B;
			2'b11: result[3:0] = ~t_A;
			default: $display("ERROR. Valor no esperado para t_Op: %b", t_Op);
		endcase
		flag_carry = 1'bx;
		flag_sign = 1'bx;
	end
	else
	begin
		case (t_Op)
			2'b00: result = t_A + t_B;
			2'b01: result = t_A + ((t_B ^4'b1111) + 1);
			2'b10: result = (t_A ^4'b1111) + 4'b0001;
			2'b11: result = (t_B ^4'b1111) + 4'b0001;
			default: $display("ERROR. Valor no esperado para t_Op: %b", t_Op);
		endcase
		flag_carry = result[4];
		flag_sign = result[3];
	if (flag_sign !== t_s || flag_carry !== t_c)
		begin
		errores = errores + 1;
		$display("ERROR con operación L=%b, OP=%b A=%b B=%b", t_L, t_Op, t_A, t_B);
		if (flag_sign !== t_s)
			$display("ERROR. Flag de signo esperado %b, obtenido %b", flag_sign, t_s);
		if (flag_carry !== t_c)
			$display("\tFlag de acarreo esperado %b, obtenido %b", flag_carry, t_c);
		end
	end
	flag_zero = ~| result[3:0];
	if (result[3:0] !== t_R || flag_zero !== t_z)
		begin
		errores = errores + 1;
		$display("ERROR con operación L=%b, OP=%b A=%b B=%b", t_L, t_Op, t_A, t_B);
		if (result[3:0] !== t_R)
			$display("\tResultado esperado %b, obtenido %b", result[3:0], t_R);
		if (flag_zero !== t_z)
			$display("\tFlag de cero esperado %b, obtenido %b", flag_zero, t_z);
		end
end
endtask
endmodule

prácticas/p1.2/sim/alu.vcd
$date
	Thu Nov 12 10:01:02 2020
$end
$version
	Icarus Verilog
$end
$timescale
	10ps
$end
$scope module alu_tb $end
$var wire 1 ! t_z $end
$var wire 1 " t_s $end
$var wire 1 # t_c $end
$var wire 4 $ t_R [3:0] $end
$var reg 4 % t_A [3:0] $end
$var reg 4 & t_B [3:0] $end
$var reg 1 ' t_L $end
$var reg 2 ( t_Op [1:0] $end
$var integer 32 ) errores [31:0] $end
$scope module mat $end
$var wire 4 * A [3:0] $end
$var wire 2 + ALUOp [1:0] $end
$var wire 4 , B [3:0] $end
$var wire 1 ' L $end
$var wire 1 - cin $end
$var wire 1 . cpl $end
$var wire 1 / op1_A $end
$var wire 1 0 op2_B $end
$var wire 1 1 out_big_or $end
$var wire 1 ! zero $end
$var wire 1 " sign $end
$var wire 4 2 carry_inner [3:0] $end
$var wire 1 # carry $end
$var wire 4 3 R [3:0] $end
$var wire 4 4 OP_inner [3:0] $end
$var wire 4 5 OP2 [3:0] $end
$var wire 4 6 OP1 [3:0] $end
$scope module cal1 $end
$var wire 1 7 a $end
$var wire 1 8 b $end
$var wire 1 - c_in $end
$var wire 1 ' l $end
$var wire 2 9 s [1:0] $end
$var wire 1 : sum_inner $end
$var wire 1 ; out $end
$var wire 1 < cl_inner $end
$var wire 1 = c_out $end
$scope module cl1 $end
$var wire 1 7 a $end
$var wire 1 8 b $end
$var wire 2 > s [1:0] $end
$var reg 1 < out $end
$upscope $end
$scope module fa1 $end
$var wire 1 7 a $end
$var wire 1 8 b $end
$var wire 1 - cin $end
$var wire 1 : sum $end
$var wire 1 = cout $end
$upscope $end
$scope module mux1 $end
$var wire 1 : a $end
$var wire 1 < b $end
$var wire 1 ' s $end
$var wire 1 ; out $end
$upscope $end
$upscope $end
$scope module cal2 $end
$var wire 1 ? a $end
$var wire 1 @ b $end
$var wire 1 A c_in $end
$var wire 1 ' l $end
$var wire 2 B s [1:0] $end
$var wire 1 C sum_inner $end
$var wire 1 D out $end
$var wire 1 E cl_inner $end
$var wire 1 F c_out $end
$scope module cl1 $end
$var wire 1 ? a $end
$var wire 1 @ b $end
$var wire 2 G s [1:0] $end
$var reg 1 E out $end
$upscope $end
$scope module fa1 $end
$var wire 1 ? a $end
$var wire 1 @ b $end
$var wire 1 A cin $end
$var wire 1 C sum $end
$var wire 1 F cout $end
$upscope $end
$scope module mux1 $end
$var wire 1 C a $end
$var wire 1 E b $end
$var wire 1 ' s $end
$var wire 1 D out $end
$upscope $end
$upscope $end
$scope module cal3 $end
$var wire 1 H a $end
$var wire 1 I b $end
$var wire 1 J c_in $end
$var wire 1 ' l $end
$var wire 2 K s [1:0] $end
$var wire 1 L sum_inner $end
$var wire 1 M out $end
$var wire 1 N cl_inner $end
$var wire 1 O c_out $end
$scope module cl1 $end
$var wire 1 H a $end
$var wire 1 I b $end
$var wire 2 P s [1:0] $end
$var reg 1 N out $end
$upscope $end
$scope module fa1 $end
$var wire 1 H a $end
$var wire 1 I b $end
$var wire 1 J cin $end
$var wire 1 L sum $end
$var wire 1 O cout $end
$upscope $end
$scope module mux1 $end
$var wire 1 L a $end
$var wire 1 N b $end
$var wire 1 ' s $end
$var wire 1 M out $end
$upscope $end
$upscope $end
$scope module cal4 $end
$var wire 1 Q a $end
$var wire 1 R b $end
$var wire 1 S c_in $end
$var wire 1 ' l $end
$var wire 2 T s [1:0] $end
$var wire 1 U sum_inner $end
$var wire 1 V out $end
$var wire 1 W cl_inner $end
$var wire 1 # c_out $end
$scope module cl1 $end
$var wire 1 Q a $end
$var wire 1 R b $end
$var wire 2 X s [1:0] $end
$var reg 1 W out $end
$upscope $end
$scope module fa1 $end
$var wire 1 Q a $end
$var wire 1 R b $end
$var wire 1 S cin $end
$var wire 1 U sum $end
$var wire 1 # cout $end
$upscope $end
$scope module mux1 $end
$var wire 1 U a $end
$var wire 1 W b $end
$var wire 1 ' s $end
$var wire 1 V out $end
$upscope $end
$upscope $end
$scope module cpl1 $end
$var wire 1 . cpl $end
$var wire 4 Y Sal [3:0] $end
$var wire 4 Z Ent [3:0] $end
$upscope $end
$scope module mux2_A $end
$var wire 4 [ a [3:0] $end
$var wire 4 \ b [3:0] $end
$var wire 1 / s $end
$var wire 4 ] out [3:0] $end
$upscope $end
$scope module mux2_B $end
$var wire 4 ^ a [3:0] $end
$var wire 4 _ b [3:0] $end
$var wire 1 0 s $end
$var wire 4 ` out [3:0] $end
$upscope $end
$upscope $end
$scope task check $end
$var reg 1 a flag_carry $end
$var reg 1 b flag_sign $end
$var reg 1 c flag_zero $end
$var reg 5 d result [4:0] $end
$upscope $end
$upscope $end
$scope module mux4_1 $end
$var wire 1 e e0 $end
$var wire 1 f e1 $end
$var wire 1 g e2 $end
$var wire 1 h e3 $end
$var wire 2 i s [1:0] $end
$var reg 1 j out $end
$upscope $end
$enddefinitions $end
#0
$dumpvars
xj
bz i
zh
zg
zf
ze
bx d
xc
xb
xa
b0 `
b0 _
b0 ^
b0 ]
b0 \
b0 [
b0 Z
b0 Y
b0 X
0W
0V
0U
b0 T
0S
0R
0Q
b0 P
0O
0N
0M
0L
b0 K
0J
0I
0H
b0 G
0F
0E
0D
0C
b0 B
0A
0@
0?
b0 >
0=
0<
0;
0:
b0 9
08
07
b0 6
b0 5
b0 4
b0 3
b0z 2
01
10
1/
0.
0-
b0 ,
b0 +
b0 *
b0 )
b0 (
0'
b0 &
b0 %
b0 $
0#
0"
1!
$end
#200
0!
11
b1 $
b1 3
1;
1:
18
b1 5
b1 Y
b1 4
b1 Z
b1 `
b1 &
b1 ,
b1 _
1c
0b
0a
b0 d
#400
1D
b10 $
b10 3
0;
1C
0:
1@
08
b10 5
b10 Y
b10 4
b10 Z
b10 `
b10 &
b10 ,
b10 _
0c
b1 d
#600
b11 $
b11 3
1;
1:
18
b11 5
b11 Y
b11 4
b11 Z
b11 `
b11 &
b11 ,
b11 _
b10 d
#800
1M
0D
b100 $
b100 3
0;
1L
0C
0:
1I
0@
08
b100 5
b100 Y
b100 4
b100 Z
b100 `
b100 &
b100 ,
b100 _
b11 d
#1000
b101 $
b101 3
1;
1:
18
b101 5
b101 Y
b101 4
b101 Z
b101 `
b101 &
b101 ,
b101 _
b100 d
#1200
1D
b110 $
b110 3
0;
1C
0:
1@
08
b110 5
b110 Y
b110 4
b110 Z
b110 `
b110 &
b110 ,
b110 _
b101 d
#1400
b111 $
b111 3
1;
1:
18
b111 5
b111 Y
b111 4
b111 Z
b111 `
b111 &
b111 ,
b111 _
b110 d
#1600
1"
1V
0M
0D
b1000 $
b1000 3
0;
1U
0L
0C
0:
1R
0I
0@
08
b1000 5
b1000 Y
b1000 4
b1000 Z
b1000 `
b1000 &
b1000 ,
b1000 _
b111 d
#1800
b1001 $
b1001 3
1;
1:
18
b1001 5
b1001 Y
b1001 4
b1001 Z
b1001 `
b1001 &
b1001 ,
b1001 _
1b
b1000 d
#2000
1D
b1010 $
b1010 3
0;
1C
0:
1@
08
b1010 5
b1010 Y
b1010 4
b1010 Z
b1010 `
b1010 &
b1010 ,
b1010 _
b1001 d
#2200
b1011 $
b1011 3
1;
1:
18
b1011 5
b1011 Y
b1011 4
b1011 Z
b1011 `
b1011 &
b1011 ,
b1011 _
b1010 d
#2400
1M
0D
b1100 $
b1100 3
0;
1L
0C
0:
1I
0@
08
b1100 5
b1100 Y
b1100 4
b1100 Z
b1100 `
b1100 &
b1100 ,
b1100 _
b1011 d
#2600
b1101 $
b1101 3
1;
1:
18
b1101 5
b1101 Y
b1101 4
b1101 Z
b1101 `
b1101 &
b1101 ,
b1101 _
b1100 d
#2800
1D
b1110 $
b1110 3
0;
1C
0:
1@
08
b1110 5
b1110 Y
b1110 4
b1110 Z
b1110 `
b1110 &
b1110 ,
b1110 _
b1101 d
#3000
b1111 $
b1111 3
1;
1:
18
b1111 5
b1111 Y
b1111 4
b1111 Z
b1111 `
b1111 &
b1111 ,
b1111 _
b1110 d
#3200
0"
0V
0M
b1 $
b1 3
0D
0U
0L
0C
0R
0I
0@
08
17
b0 5
b0 Y
b1 6
b1 ]
b0 4
b0 Z
b0 `
b1 %
b1 *
b1 \
b1 ^
b0 &
b0 ,
b0 _
b1111 d
#3400
0!
11
1D
1C
b10 $
b10 3
0;
1A
1<
0:
b1z 2
1=
18
b1 5
b1 Y
b1 4
b1 Z
b1 `
b1 &
b1 ,
b1 _
0b
b1 d
#3600
0M
0L
1D
0J
b11 $
b11 3
1;
0A
1C
0F
0<
1:
b0z 2
0=
1@
08
b10 5
b10 Y
b10 4
b10 Z
b10 `
b10 &
b10 ,
b10 _
b10 d
#3800
0!
11
1M
1L
0D
1J
0C
1F
b100 $
b100 3
0;
1A
1<
0:
b11z 2
1=
18
b11 5
b11 Y
b11 4
b11 Z
b11 `
b11 &
b11 ,
b11 _
b11 d
#4000
0"
0V
0U
1M
0S
0D
0J
b101 $
b101 3
1;
0A
1L
0O
0C
0F
0<
1:
b0z 2
0=
1I
0@
08
b100 5
b100 Y
b100 4
b100 Z
b100 `
b100 &
b100 ,
b100 _
b100 d
#4200
1D
1C
b110 $
b110 3
0;
1A
1<
0:
b1z 2
1=
18
b101 5
b101 Y
b101 4
b101 Z
b101 `
b101 &
b101 ,
b101 _
b101 d
#4400
0"
0V
0U
1M
0S
1L
0O
1D
0J
b111 $
b111 3
1;
0A
1C
0F
0<
1:
b0z 2
0=
1@
08
b110 5
b110 Y
b110 4
b110 Z
b110 `
b110 &
b110 ,
b110 _
b110 d
#4600
0!
1"
11
1V
1U
0M
1S
0L
1O
0D
1J
0C
1F
b1000 $
b1000 3
0;
1A
1<
0:
b111z 2
1=
18
b111 5
b111 Y
b111 4
b111 Z
b111 `
b111 &
b111 ,
b111 _
b111 d
#4800
1"
1V
0M
0S
0D
0J
b1001 $
b1001 3
1;
0A
1U
0#
0L
0O
0C
0F
0<
1:
b0z 2
0=
1R
0I
0@
08
b1000 5
b1000 Y
b1000 4
b1000 Z
b1000 `
b1000 &
b1000 ,
b1000 _
1b
b1000 d
#5000
1D
1C
b1010 $
b1010 3
0;
1A
1<
0:
b1z 2
1=
18
b1001 5
b1001 Y
b1001 4
b1001 Z
b1001 `
b1001 &
b1001 ,
b1001 _
b1001 d
#5200
0M
0L
1D
0J
b1011 $
b1011 3
1;
0A
1C
0F
0<
1:
b0z 2
0=
1@
08
b1010 5
b1010 Y
b1010 4
b1010 Z
b1010 `
b1010 &
b1010 ,
b1010 _
b1010 d
#5400
1M
1L
0D
1J
0C
1F
b1100 $
b1100 3
0;
1A
1<
0:
b11z 2
1=
18
b1011 5
b1011 Y
b1011 4
b1011 Z
b1011 `
b1011 &
b1011 ,
b1011 _
b1011 d
#5600
1"
1V
1U
0#
1M
0S
0D
0J
b1101 $
b1101 3
1;
0A
1L
0O
0C
0F
0<
1:
b0z 2
0=
1I
0@
08
b1100 5
b1100 Y
b1100 4
b1100 Z
b1100 `
b1100 &
b1100 ,
b1100 _
b1100 d
#5800
1D
1C
b1110 $
b1110 3
0;
1A
1<
0:
b1z 2
1=
18
b1101 5
b1101 Y
b1101 4
b1101 Z
b1101 `
b1101 &
b1101 ,
b1101 _
b1101 d
#6000
1"
1V
1U
0#
1M
0S
1L
0O
1D
0J
b1111 $
b1111 3
1;
0A
1C
0F
0<
1:
b0z 2
0=
1@
08
b1110 5
b1110 Y
b1110 4
b1110 Z
b1110 `
b1110 &
b1110 ,
b1110 _
b1110 d
#6200
1!
01
0"
0V
0U
1#
0M
1S
0L
1O
0D
1J
0C
1F
b0 $
b0 3
0;
1A
1<
0:
b111z 2
1=
18
b1111 5
b1111 Y
b1111 4
b1111 Z
b1111 `
b1111 &
b1111 ,
b1111 _
b1111 d
#6400
0!
11
1D
0J
0"
1C
0F
0V
b10 $
b10 3
0M
0S
0A
0U
0#
0L
0O
0<
b0z 2
0=
0R
0I
0@
08
1?
07
b0 5
b0 Y
b10 6
b10 ]
b0 4
b0 Z
b0 `
b10 %
b10 *
b10 \
b10 ^
b0 &
b0 ,
b0 _
1c
0b
1a
b10000 d
#6600
b11 $
b11 3
1;
1:
18
b1 5
b1 Y
b1 4
b1 Z
b1 `
b1 &
b1 ,
b1 _
0c
0a
b10 d
#6800
0!
1M
11
1L
0D
1J
b100 $
b100 3
0;
1E
0C
b10z 2
1F
0:
1@
08
b10 5
b10 Y
b10 4
b10 Z
b10 `
b10 &
b10 ,
b10 _
b11 d
#7000
b101 $
b101 3
1;
1:
18
b11 5
b11 Y
b11 4
b11 Z
b11 `
b11 &
b11 ,
b11 _
b100 d
#7200
0"
0V
0U
1M
0S
1D
0J
b110 $
b110 3
0;
1L
0O
0E
1C
b0z 2
0F
0:
1I
0@
08
b100 5
b100 Y
b100 4
b100 Z
b100 `
b100 &
b100 ,
b100 _
b101 d
#7400
b111 $
b111 3
1;
1:
18
b101 5
b101 Y
b101 4
b101 Z
b101 `
b101 &
b101 ,
b101 _
b110 d
#7600
0!
1"
11
1V
1U
0M
1S
0L
1O
0D
1J
b1000 $
b1000 3
0;
1E
0C
b110z 2
1F
0:
1@
08
b110 5
b110 Y
b110 4
b110 Z
b110 `
b110 &
b110 ,
b110 _
b111 d
#7800
b1001 $
b1001 3
1;
1:
18
b111 5
b111 Y
b111 4
b111 Z
b111 `
b111 &
b111 ,
b111 _
1b
b1000 d
#8000
1"
1V
0M
0S
1D
0J
b1010 $
b1010 3
0;
1U
0#
0L
0O
0E
1C
b0z 2
0F
0:
1R
0I
0@
08
b1000 5
b1000 Y
b1000 4
b1000 Z
b1000 `
b1000 &
b1000 ,
b1000 _
b1001 d
#8200
b1011 $
b1011 3
1;
1:
18
b1001 5
b1001 Y
b1001 4
b1001 Z
b1001 `
b1001 &
b1001 ,
b1001 _
b1010 d
#8400
1M
1L
0D
1J
b1100 $
b1100 3
0;
1E
0C
b10z 2
1F
0:
1@
08
b1010 5
b1010 Y
b1010 4
b1010 Z
b1010 `
b1010 &
b1010 ,
b1010 _
b1011 d
#8600
b1101 $
b1101 3
1;
1:
18
b1011 5
b1011 Y
b1011 4
b1011 Z
b1011 `
b1011 &
b1011 ,
b1011 _
b1100 d
#8800
1"
1V
1U
0#
1M
0S
1D
0J
b1110 $
b1110 3
0;
1L
0O
0E
1C
b0z 2
0F
0:
1I
0@
08
b1100 5
b1100 Y
b1100 4
b1100 Z
b1100 `
b1100 &
b1100 ,
b1100 _
b1101 d
#9000
b1111 $
b1111 3
1;
1:
18
b1101 5
b1101 Y
b1101 4
b1101 Z
b1101 `
b1101 &
b1101 ,
b1101 _
b1110 d
#9200
1!
01
0"
0V
0U
1#
0M
1S
0L
1O
0D
1J
b0 $
b0 3
0;
1E
0C
b110z 2
1F
0:
1@
08
b1110 5
b1110 Y
b1110 4
b1110 Z
b1110 `
b1110 &
b1110 ,
b1110 _
b1111 d
#9400
0!
11
b1 $
b1 3
1;
1:
18
b1111 5
b1111 Y
b1111 4
b1111 Z
b1111 `
b1111 &
b1111 ,
b1111 _
1c
0b
1a
b10000 d
#9600
0"
0V
0M
0S
b11 $
b11 3
1D
0J
0U
0#
0L
0O
0E
1C
b0z 2
0F
0R
0I
0@
08
17
b0 5
b0 Y
b11 6
b11 ]
b0 4
b0 Z
b0 `
b11 %
b11 *
b11 \
b11 ^
b0 &
b0 ,
b0 _
0c
b10001 d
#9800
0!
11
1M
1L
0D
1J
0C
1F
b100 $
b100 3
0;
1A
1<
0:
b11z 2
1=
18
b1 5
b1 Y
b1 4
b1 Z
b1 `
b1 &
b1 ,
b1 _
0a
b11 d
#10000
0D
b101 $
b101 3
1;
0A
1E
0C
0<
1:
b10z 2
0=
1@
08
b10 5
b10 Y
b10 4
b10 Z
b10 `
b10 &
b10 ,
b10 _
b100 d
#10200
1D
1C
b110 $
b110 3
0;
1A
1<
0:
b11z 2
1=
18
b11 5
b11 Y
b11 4
b11 Z
b11 `
b11 &
b11 ,
b11 _
b101 d
#10400
0"
0V
0J
0U
0F
1M
0S
1D
b111 $
b111 3
1;
0A
1L
0O
0E
1C
0<
1:
b0z 2
0=
1I
0@
08
b100 5
b100 Y
b100 4
b100 Z
b100 `
b100 &
b100 ,
b100 _
b110 d
#10600
0!
1"
11
1V
1U
0M
1S
0L
1O
0D
1J
0C
1F
b1000 $
b1000 3
0;
1A
1<
0:
b111z 2
1=
18
b101 5
b101 Y
b101 4
b101 Z
b101 `
b101 &
b101 ,
b101 _
b111 d
#10800
0D
b1001 $
b1001 3
1;
0A
1E
0C
0<
1:
b110z 2
0=
1@
08
b110 5
b110 Y
b110 4
b110 Z
b110 `
b110 &
b110 ,
b110 _
1b
b1000 d
#11000
1D
1C
b1010 $
b1010 3
0;
1A
1<
0:
b111z 2
1=
18
b111 5
b111 Y
b111 4
b111 Z
b111 `
b111 &
b111 ,
b111 _
b1001 d
#11200
0J
1"
0F
1V
0M
0S
1D
b1011 $
b1011 3
1;
0A
1U
0#
0L
0O
0E
1C
0<
1:
b0z 2
0=
1R
0I
0@
08
b1000 5
b1000 Y
b1000 4
b1000 Z
b1000 `
b1000 &
b1000 ,
b1000 _
b1010 d
#11400
1M
1L
0D
1J
0C
1F
b1100 $
b1100 3
0;
1A
1<
0:
b11z 2
1=
18
b1001 5
b1001 Y
b1001 4
b1001 Z
b1001 `
b1001 &
b1001 ,
b1001 _
b1011 d
#11600
0D
b1101 $
b1101 3
1;
0A
1E
0C
0<
1:
b10z 2
0=
1@
08
b1010 5
b1010 Y
b1010 4
b1010 Z
b1010 `
b1010 &
b1010 ,
b1010 _
b1100 d
#11800
1D
1C
b1110 $
b1110 3
0;
1A
1<
0:
b11z 2
1=
18
b1011 5
b1011 Y
b1011 4
b1011 Z
b1011 `
b1011 &
b1011 ,
b1011 _
b1101 d
#12000
1"
1V
0J
1U
0#
0F
1M
0S
1D
b1111 $
b1111 3
1;
0A
1L
0O
0E
1C
0<
1:
b0z 2
0=
1I
0@
08
b1100 5
b1100 Y
b1100 4
b1100 Z
b1100 `
b1100 &
b1100 ,
b1100 _
b1110 d
#12200
1!
01
0"
0V
0U
1#
0M
1S
0L
1O
0D
1J
0C
1F
b0 $
b0 3
0;
1A
1<
0:
b111z 2
1=
18
b1101 5
b1101 Y
b1101 4
b1101 Z
b1101 `
b1101 &
b1101 ,
b1101 _
b1111 d
#12400
0!
11
0D
b1 $
b1 3
1;
0A
1E
0C
0<
1:
b110z 2
0=
1@
08
b1110 5
b1110 Y
b1110 4
b1110 Z
b1110 `
b1110 &
b1110 ,
b1110 _
1c
0b
1a
b10000 d
#12600
0!
11
1D
1C
b10 $
b10 3
0;
1A
1<
0:
b111z 2
1=
18
b1111 5
b1111 Y
b1111 4
b1111 Z
b1111 `
b1111 &
b1111 ,
b1111 _
0c
b10001 d
#12800
1M
0S
0D
0"
1L
0O
0C
b100 $
b100 3
0V
0J
0A
0U
0#
0F
0E
0<
b0z 2
0=
0R
0I
0@
08
1H
0?
07
b0 5
b0 Y
b100 6
b100 ]
b0 4
b0 Z
b0 `
b100 %
b100 *
b100 \
b100 ^
b0 &
b0 ,
b0 _
b10010 d
#13000
b101 $
b101 3
1;
1:
18
b1 5
b1 Y
b1 4
b1 Z
b1 `
b1 &
b1 ,
b1 _
0a
b100 d
#13200
1D
b110 $
b110 3
0;
1C
0:
1@
08
b10 5
b10 Y
b10 4
b10 Z
b10 `
b10 &
b10 ,
b10 _
b101 d
#13400
b111 $
b111 3
1;
1:
18
b11 5
b11 Y
b11 4
b11 Z
b11 `
b11 &
b11 ,
b11 _
b110 d
#13600
1"
0!
1V
11
1U
0M
1S
0D
b1000 $
b1000 3
0;
1N
0L
b100z 2
1O
0C
0:
1I
0@
08
b100 5
b100 Y
b100 4
b100 Z
b100 `
b100 &
b100 ,
b100 _
b111 d
#13800
b1001 $
b1001 3
1;
1:
18
b101 5
b101 Y
b101 4
b101 Z
b101 `
b101 &
b101 ,
b101 _
1b
b1000 d
#14000
1D
b1010 $
b1010 3
0;
1C
0:
1@
08
b110 5
b110 Y
b110 4
b110 Z
b110 `
b110 &
b110 ,
b110 _
b1001 d
#14200
b1011 $
b1011 3
1;
1:
18
b111 5
b111 Y
b111 4
b111 Z
b111 `
b111 &
b111 ,
b111 _
b1010 d
#14400
1"
1V
1M
0S
0D
b1100 $
b1100 3
0;
1U
0#
0N
1L
b0z 2
0O
0C
0:
1R
0I
0@
08
b1000 5
b1000 Y
b1000 4
b1000 Z
b1000 `
b1000 &
b1000 ,
b1000 _
b1011 d
#14600
b1101 $
b1101 3
1;
1:
18
b1001 5
b1001 Y
b1001 4
b1001 Z
b1001 `
b1001 &
b1001 ,
b1001 _
b1100 d
#14800
1D
b1110 $
b1110 3
0;
1C
0:
1@
08
b1010 5
b1010 Y
b1010 4
b1010 Z
b1010 `
b1010 &
b1010 ,
b1010 _
b1101 d
#15000
b1111 $
b1111 3
1;
1:
18
b1011 5
b1011 Y
b1011 4
b1011 Z
b1011 `
b1011 &
b1011 ,
b1011 _
b1110 d
#15200
1!
01
0"
0V
0U
1#
0M
1S
0D
b0 $
b0 3
0;
1N
0L
b100z 2
1O
0C
0:
1I
0@
08
b1100 5
b1100 Y
b1100 4
b1100 Z
b1100 `
b1100 &
b1100 ,
b1100 _
b1111 d
#15400
0!
11
b1 $
b1 3
1;
1:
18
b1101 5
b1101 Y
b1101 4
b1101 Z
b1101 `
b1101 &
b1101 ,
b1101 _
1c
0b
1a
b10000 d
#15600
1D
b10 $
b10 3
0;
1C
0:
1@
08
b1110 5
b1110 Y
b1110 4
b1110 Z
b1110 `
b1110 &
b1110 ,
b1110 _
0c
b10001 d
#15800
b11 $
b11 3
1;
1:
18
b1111 5
b1111 Y
b1111 4
b1111 Z
b1111 `
b1111 &
b1111 ,
b1111 _
b10010 d
#16000
0"
0V
1M
0S
b101 $
b101 3
0D
0U
0#
0N
1L
b0z 2
0O
0C
0R
0I
0@
08
17
b0 5
b0 Y
b101 6
b101 ]
b0 4
b0 Z
b0 `
b101 %
b101 *
b101 \
b101 ^
b0 &
b0 ,
b0 _
b10011 d
#16200
1D
1C
b110 $
b110 3
0;
1A
1<
0:
b1z 2
1=
18
b1 5
b1 Y
b1 4
b1 Z
b1 `
b1 &
b1 ,
b1 _
0a
b101 d
#16400
0"
0V
0U
1M
0S
1L
0O
1D
0J
b111 $
b111 3
1;
0A
1C
0F
0<
1:
b0z 2
0=
1@
08
b10 5
b10 Y
b10 4
b10 Z
b10 `
b10 &
b10 ,
b10 _
b110 d
#16600
0!
1"
11
1V
1U
0M
1S
0L
1O
0D
1J
0C
1F
b1000 $
b1000 3
0;
1A
1<
0:
b111z 2
1=
18
b11 5
b11 Y
b11 4
b11 Z
b11 `
b11 &
b11 ,
b11 _
b111 d
#16800
0M
0D
0J
b1001 $
b1001 3
1;
0A
1N
0L
0C
0F
0<
1:
b100z 2
0=
1I
0@
08
b100 5
b100 Y
b100 4
b100 Z
b100 `
b100 &
b100 ,
b100 _
1b
b1000 d
#17000
1D
1C
b1010 $
b1010 3
0;
1A
1<
0:
b101z 2
1=
18
b101 5
b101 Y
b101 4
b101 Z
b101 `
b101 &
b101 ,
b101 _
b1001 d
#17200
0M
0L
1D
0J
b1011 $
b1011 3
1;
0A
1C
0F
0<
1:
b100z 2
0=
1@
08
b110 5
b110 Y
b110 4
b110 Z
b110 `
b110 &
b110 ,
b110 _
b1010 d
