prácticas/p1.2/mods/compl1.v

module compl1 (output wire [3:0] Sal, input wire [3:0] Ent, input wire cpl);

	assign Sal = cpl ? ~Ent : Ent;

endmodule

prácticas/p1.2/mods/mux4_1.v

module mux4_1 (output reg out, input wire e0, e1, e2, e3, input wire [1:0] s);

always@ (e0, e1, e2, e3, s)
	begin
	case(s)
		2'b00 : out = e0;
		2'b01 : out = e1;
		2'b10 : out = e2;
		2'b11 : out = e3;
		default: out = 1'bx;
	endcase
	end

endmodule

prácticas/p1.2/deps/cl.v
module cl (output wire out, input wire a, b, input wire [1:0] s);

	// cables que intercanectan las puertas con el MUX
	wire s_and, s_or, s_xor, s_not;

	// interconexiones
	and    and1 (s_and, a, b);
	or 	   or1 	(s_or, a, b);
	xor    xor1 (s_xor, a, b);
	not    not1 (s_not, a);
	mux4_1 mux 	(out, s_and, s_or, s_xor, s_not, s);

endmodule

prácticas/p1.2/mods/fa.v

module fa (output wire cout, sum, input wire a, b, cin);

	assign {cout, sum} = a + b + cin;

endmodule

prácticas/p1.2/mods/cal.v
// celda aritmético-lógica
module cal (output wire out, c_out, input wire a, b, l, c_in, input wire [1:0] s);

	// sum_int: salida del full adder (fa), 
	// cl_int: salida de la celda lógica (cl)
	wire sum_int, cl_int;	

	fa fa1 (c_out, sum_int, a, b, c_in);
	cl cl1 (cl_int, a, b, s);
	
	// mux 2 a 1, 
	// si l=1, cl_int -> out
	// si l=0, sum_int -> out
	assign out = l ? cl_int : sum_int;

endmodule

prácticas/p1.1/mods/cal_tb.v
// Testbench para modulos fa con retardo en los semisumadores que lo componen
`timescale 1 ns / 10 ps //Directiva que fija la unidad de tiempo de simulación y el del paso de simulacion
module cal_tb;

//declaracion de señales
reg [1:0] test_s;
reg test_a, test_b, test_cin,test_d,test_l;  		//entradas 
wire test_out, test_cout;							//salidas

//instancia del modulo a testear
cal cal1(test_out, test_cout, test_a, test_b, test_l, test_cin, test_s);

initial
begin
  $monitor("tiempo=%0d a=%b b=%b l=%b cin=%b s=%b out=%b cout=%b", $time, test_a, test_b,test_l, test_cin,test_s, test_out, test_cout);
  $dumpfile("fa_v2_tb.vcd");
  $dumpvars;
  //vector de test 0
  test_cin = 1'b0;
  test_a = 1'b0;
  test_b = 1'b0;   //out = 0 c_out = 0
  test_l = 1'b0;
  test_s = 2'b00;
  
  # 20;
  //vector de test 1
  test_cin = 1'b0;
  test_a = 1'b0;
  test_b = 1'b1;   //out = 0
  test_l = 1'b1;
  test_s = 2'b00;
  # 20;
  //vector de test 2
  test_cin = 1'b0;
  test_a = 1'b1;
  test_b = 1'b0;	//out = 1
  test_l = 1'b1;
  test_s = 2'b10;
  # 20;
  //vector de test 3
  test_cin = 1'b0;
  test_a = 1'b1;
  test_b = 1'b1;    //out = 0
  test_l = 1'b1;
  test_s = 2'b11;
  # 20;
  //vector de test 4
  test_cin = 1'b1;
  test_a = 1'b0;
  test_b = 1'b0;	//out = 1 c_out = 0
  test_l = 1'b0;
  test_s = 2'b10;
  # 20;
  //vector de test 5
  test_cin = 1'b1;
  test_a = 1'b0;
  test_b = 1'b1;
  test_l = 1'b0;
  test_s = 2'b11;
  # 20;
  //vector de test 6
  test_cin = 1'b1;
  test_a = 1'b1;
  test_b = 1'b0;
  test_l = 1'b0;
  test_s = 2'b00;
  # 20;
  //vector de test 7
  test_cin = 1'b1;
  test_a = 1'b1;
  test_b = 1'b1;
  test_l = 1'b0;
  test_s = 2'b00;
  # 20;
  //fin simulacion
  $finish;
end

endmodule

prácticas/p1.2/sim/fa_v2_tb.vcd
$date
	Thu Nov 05 09:05:44 2020
$end
$version
	Icarus Verilog
$end
$timescale
	10ps
$end
$scope module cal_tb $end
$var wire 1 ! test_out $end
$var wire 1 " test_cout $end
$var reg 1 # test_a $end
$var reg 1 $ test_b $end
$var reg 1 % test_cin $end
$var reg 1 & test_l $end
$var reg 2 ' test_s [1:0] $end
$scope module cal1 $end
$var wire 1 # a $end
$var wire 1 $ b $end
$var wire 1 % c_in $end
$var wire 1 & l $end
$var wire 2 ( s [1:0] $end
$var wire 1 ) sum_int $end
$var wire 1 ! out $end
$var wire 1 * cl_int $end
$var wire 1 " c_out $end
$scope module cl1 $end
$var wire 1 # a $end
$var wire 1 $ b $end
$var wire 2 + s [1:0] $end
$var wire 1 , s_and $end
$var wire 1 - s_not $end
$var wire 1 . s_or $end
$var wire 1 / s_xor $end
$var wire 1 * out $end
$scope module mux $end
$var wire 1 , e0 $end
$var wire 1 . e1 $end
$var wire 1 / e2 $end
$var wire 1 - e3 $end
$var wire 2 0 s [1:0] $end
$var reg 1 * out $end
$upscope $end
$upscope $end
$scope module fa1 $end
$var wire 1 # a $end
$var wire 1 $ b $end
$var wire 1 % cin $end
$var wire 1 ) sum $end
$var wire 1 " cout $end
$upscope $end
$upscope $end
$upscope $end
$scope module compl1 $end
$var wire 4 1 Ent [3:0] $end
$var wire 1 2 cpl $end
$var wire 4 3 Sal [3:0] $end
$upscope $end
$enddefinitions $end
#0
$dumpvars
bz 3
z2
bz 1
b0 0
0/
0.
1-
0,
b0 +
0*
0)
b0 (
b0 '
0&
0%
0$
0#
0"
0!
$end
#2000
1.
1/
1)
1&
1$
#4000
1!
1*
0-
b10 '
b10 (
b10 +
b10 0
0$
1#
#6000
0!
0*
1,
0/
0)
1"
b11 '
b11 (
b11 +
b11 0
1$
#8000
1!
0"
0,
0.
1-
1)
b10 '
b10 (
b10 +
b10 0
0&
0$
0#
1%
#10000
0!
1*
1.
1/
0)
1"
b11 '
b11 (
b11 +
b11 0
1$
#12000
0*
0-
b0 '
b0 (
b0 +
b0 0
0$
1#
#14000
1*
1!
1,
0/
1)
1$
